minecraft_textcraft/__init__.py
minecraft_textcraft/__main__.py
minecraft_textcraft/add.py
minecraft_textcraft/animate.py
minecraft_textcraft/colorize_ascii.py
minecraft_textcraft/commands.py
minecraft_textcraft/font_data.py
minecraft_textcraft/render.py
minecraft_textcraft/sample_commands.py
minecraft_textcraft-1.0.1.dist-info/licenses/LICENSE
minecraft_textcraft-1.0.1.dist-info/METADATA
minecraft_textcraft-1.0.1.dist-info/WHEEL
minecraft_textcraft-1.0.1.dist-info/entry_points.txt
minecraft_textcraft-1.0.1.dist-info/top_level.txt
minecraft_textcraft-1.0.1.dist-info/RECORD
