Metadata-Version: 2.4
Name: minecraft-textcraft
Version: 1.0.1
Summary: A Python package that converts text into blocky Minecraft-style ASCII art...
License-Expression: GPL-3.0-or-later
Classifier: Programming Language :: Python :: 3
Classifier: Intended Audience :: Education
Classifier: Operating System :: OS Independent
Requires-Python: >=3.7
License-File: LICENSE
Provides-Extra: dev
Requires-Dist: pytest; extra == "dev"
Requires-Dist: build; extra == "dev"
Dynamic: license-file
